[
null,
{"id":1,"animationId":0,"consumable":false,"damage":{"critical":false,"elementId":0,"formula":"0","type":0,"variance":20},"description":"","effects":[{"code":44,"dataId":234,"value1":1,"value2":0}],"hitType":0,"iconIndex":145,"itypeId":2,"name":"Bague de Charles","note":"","occasion":2,"price":0,"repeats":1,"scope":0,"speed":0,"successRate":100,"tpGain":0},
{"id":2,"animationId":0,"consumable":false,"damage":{"critical":false,"elementId":0,"formula":"0","type":0,"variance":20},"description":"","effects":[],"hitType":0,"iconIndex":1648,"itypeId":2,"name":"clef du dortoir","note":"","occasion":2,"price":0,"repeats":1,"scope":0,"speed":0,"successRate":100,"tpGain":0},
{"id":3,"animationId":0,"consumable":false,"damage":{"critical":false,"elementId":0,"formula":"0","type":0,"variance":20},"description":"","effects":[],"hitType":0,"iconIndex":124,"itypeId":2,"name":"Tournevis","note":"","occasion":2,"price":0,"repeats":1,"scope":0,"speed":0,"successRate":100,"tpGain":0},
{"id":4,"animationId":0,"consumable":false,"damage":{"critical":false,"elementId":0,"formula":"0","type":0,"variance":20},"description":"","effects":[],"hitType":0,"iconIndex":215,"itypeId":2,"name":"Corde","note":"","occasion":2,"price":0,"repeats":1,"scope":0,"speed":0,"successRate":100,"tpGain":0},
{"id":5,"animationId":0,"consumable":false,"damage":{"critical":false,"elementId":0,"formula":"0","type":0,"variance":20},"description":"","effects":[],"hitType":0,"iconIndex":1936,"itypeId":2,"name":"Planche en bois","note":"","occasion":2,"price":0,"repeats":1,"scope":0,"speed":0,"successRate":100,"tpGain":0},
{"id":6,"animationId":0,"consumable":false,"damage":{"critical":false,"elementId":0,"formula":"0","type":0,"variance":20},"description":"","effects":[],"hitType":0,"iconIndex":0,"itypeId":2,"name":"Echelle","note":"","occasion":2,"price":0,"repeats":1,"scope":0,"speed":0,"successRate":100,"tpGain":0},
{"id":7,"animationId":0,"consumable":false,"damage":{"critical":false,"elementId":0,"formula":"0","type":0,"variance":20},"description":"","effects":[],"hitType":0,"iconIndex":0,"itypeId":2,"name":"Fouet usé","note":"","occasion":2,"price":0,"repeats":1,"scope":0,"speed":0,"successRate":100,"tpGain":0},
{"id":8,"animationId":0,"consumable":false,"damage":{"critical":false,"elementId":0,"formula":"0","type":0,"variance":20},"description":"","effects":[],"hitType":0,"iconIndex":0,"itypeId":2,"name":"Livre de traffic illicite","note":"","occasion":2,"price":0,"repeats":1,"scope":0,"speed":0,"successRate":100,"tpGain":0},
{"id":9,"animationId":0,"consumable":false,"damage":{"critical":false,"elementId":0,"formula":"0","type":0,"variance":20},"description":"","effects":[],"hitType":0,"iconIndex":0,"itypeId":2,"name":"Tâche sur le sol","note":"","occasion":2,"price":0,"repeats":1,"scope":0,"speed":0,"successRate":100,"tpGain":0},
{"id":10,"animationId":0,"consumable":false,"damage":{"critical":false,"elementId":0,"formula":"0","type":0,"variance":20},"description":"","effects":[],"hitType":0,"iconIndex":0,"itypeId":2,"name":"Restes moisis","note":"","occasion":2,"price":0,"repeats":1,"scope":0,"speed":0,"successRate":100,"tpGain":0},
{"id":11,"animationId":0,"consumable":false,"damage":{"critical":false,"elementId":0,"formula":"0","type":0,"variance":20},"description":"","effects":[],"hitType":0,"iconIndex":0,"itypeId":2,"name":"Beaucoup d'alool","note":"","occasion":2,"price":0,"repeats":1,"scope":0,"speed":0,"successRate":100,"tpGain":0},
{"id":12,"animationId":0,"consumable":false,"damage":{"critical":false,"elementId":0,"formula":"0","type":0,"variance":20},"description":"","effects":[],"hitType":0,"iconIndex":0,"itypeId":2,"name":"Bris de verre ensanglanté","note":"","occasion":2,"price":0,"repeats":1,"scope":0,"speed":0,"successRate":100,"tpGain":0},
{"id":13,"animationId":0,"consumable":false,"damage":{"critical":false,"elementId":0,"formula":"0","type":0,"variance":20},"description":"","effects":[],"hitType":0,"iconIndex":0,"itypeId":2,"name":"bruit dans le grennier","note":"","occasion":2,"price":0,"repeats":1,"scope":0,"speed":0,"successRate":100,"tpGain":0},
{"id":14,"animationId":0,"consumable":false,"damage":{"critical":false,"elementId":0,"formula":"0","type":0,"variance":20},"description":"","effects":[],"hitType":0,"iconIndex":0,"itypeId":2,"name":"cadavre","note":"","occasion":2,"price":0,"repeats":1,"scope":0,"speed":0,"successRate":100,"tpGain":0},
{"id":15,"animationId":0,"consumable":false,"damage":{"critical":false,"elementId":0,"formula":"0","type":0,"variance":20},"description":"","effects":[],"hitType":0,"iconIndex":0,"itypeId":2,"name":"argent","note":"","occasion":2,"price":0,"repeats":1,"scope":0,"speed":0,"successRate":100,"tpGain":0},
{"id":16,"animationId":0,"consumable":false,"damage":{"critical":false,"elementId":0,"formula":"0","type":0,"variance":20},"description":"","effects":[],"hitType":0,"iconIndex":0,"itypeId":2,"name":"","note":"","occasion":2,"price":0,"repeats":1,"scope":0,"speed":0,"successRate":100,"tpGain":0},
{"id":17,"animationId":0,"consumable":false,"damage":{"critical":false,"elementId":0,"formula":"0","type":0,"variance":20},"description":"","effects":[],"hitType":0,"iconIndex":0,"itypeId":2,"name":"","note":"","occasion":2,"price":0,"repeats":1,"scope":0,"speed":0,"successRate":100,"tpGain":0},
{"id":18,"animationId":0,"consumable":false,"damage":{"critical":false,"elementId":0,"formula":"0","type":0,"variance":20},"description":"","effects":[],"hitType":0,"iconIndex":0,"itypeId":2,"name":"","note":"","occasion":2,"price":0,"repeats":1,"scope":0,"speed":0,"successRate":100,"tpGain":0},
{"id":19,"animationId":0,"consumable":false,"damage":{"critical":false,"elementId":0,"formula":"0","type":0,"variance":20},"description":"","effects":[],"hitType":0,"iconIndex":0,"itypeId":2,"name":"","note":"","occasion":2,"price":0,"repeats":1,"scope":0,"speed":0,"successRate":100,"tpGain":0},
{"id":20,"animationId":0,"consumable":false,"damage":{"critical":false,"elementId":0,"formula":"0","type":0,"variance":20},"description":"","effects":[],"hitType":0,"iconIndex":0,"itypeId":2,"name":"","note":"","occasion":2,"price":0,"repeats":1,"scope":0,"speed":0,"successRate":100,"tpGain":0},
{"id":21,"animationId":0,"consumable":false,"damage":{"critical":false,"elementId":0,"formula":"0","type":0,"variance":20},"description":"","effects":[],"hitType":0,"iconIndex":0,"itypeId":2,"name":"","note":"","occasion":2,"price":0,"repeats":1,"scope":0,"speed":0,"successRate":100,"tpGain":0},
{"id":22,"animationId":0,"consumable":false,"damage":{"critical":false,"elementId":0,"formula":"0","type":0,"variance":20},"description":"","effects":[],"hitType":0,"iconIndex":0,"itypeId":2,"name":"","note":"","occasion":2,"price":0,"repeats":1,"scope":0,"speed":0,"successRate":100,"tpGain":0},
{"id":23,"animationId":0,"consumable":false,"damage":{"critical":false,"elementId":0,"formula":"0","type":0,"variance":20},"description":"","effects":[],"hitType":0,"iconIndex":0,"itypeId":2,"name":"","note":"","occasion":2,"price":0,"repeats":1,"scope":0,"speed":0,"successRate":100,"tpGain":0},
{"id":24,"animationId":0,"consumable":false,"damage":{"critical":false,"elementId":0,"formula":"0","type":0,"variance":20},"description":"","effects":[],"hitType":0,"iconIndex":0,"itypeId":2,"name":"","note":"","occasion":2,"price":0,"repeats":1,"scope":0,"speed":0,"successRate":100,"tpGain":0},
{"id":25,"animationId":0,"consumable":false,"damage":{"critical":false,"elementId":0,"formula":"0","type":0,"variance":20},"description":"","effects":[],"hitType":0,"iconIndex":0,"itypeId":2,"name":"","note":"","occasion":2,"price":0,"repeats":1,"scope":0,"speed":0,"successRate":100,"tpGain":0}
]